alter_ego/__init__.py
alter_ego/agents/APIThread.py
alter_ego/agents/CLIThread.py
alter_ego/agents/ConstantThread.py
alter_ego/agents/ExternalThread.py
alter_ego/agents/GPTThread.py
alter_ego/agents/OllamaThread.py
alter_ego/agents/TextSynthThread.py
alter_ego/agents/__init__.py
alter_ego/experiment/__init__.py
alter_ego/exports/__init__.py
alter_ego/exports/otree.py
alter_ego/structure/Relay.py
alter_ego/structure/__init__.py
alter_ego/utils/__init__.py
alter_ego_llm-1.5.0.dist-info/licenses/LICENSE
ego/__init__.py
ego/cli.py
games/__init__.py
games/pd/__init__.py
games/pd/treatments.py
scenarios/__init__.py
scenarios/built.py
scenarios/ego35.py
scenarios/ego4.py
scenarios/ego_prereg.py
scenarios/mindgame.py
alter_ego_llm-1.5.0.dist-info/METADATA
alter_ego_llm-1.5.0.dist-info/WHEEL
alter_ego_llm-1.5.0.dist-info/entry_points.txt
alter_ego_llm-1.5.0.dist-info/top_level.txt
alter_ego_llm-1.5.0.dist-info/RECORD
