Metadata-Version: 2.4
Name: alter_ego_llm
Version: 1.5.0
Summary: Library to run experiments with LLMs
Home-page: https://ego.mg.sb
Author: Max R. P. Grossmann
Author-email: ego@mg.sb
Classifier: Programming Language :: Python :: 3
Classifier: License :: OSI Approved :: GNU Lesser General Public License v3 or later (LGPLv3+)
Classifier: Operating System :: OS Independent
Requires-Python: >=3.8
License-File: LICENSE
Requires-Dist: click>=8.1
Requires-Dist: colorama>=0.4.6
Requires-Dist: Jinja2>=3.1.2
Requires-Dist: openai~=1.60.2
Requires-Dist: requests<3
Requires-Dist: ollama>=0.2
Dynamic: author
Dynamic: author-email
Dynamic: classifier
Dynamic: description
Dynamic: description-content-type
Dynamic: home-page
Dynamic: license-file
Dynamic: requires-dist
Dynamic: requires-python
Dynamic: summary
